square/__init__.py
square/__main__.py
saral_squarev9-2.1.0.dist-info/LICENSE
saral_squarev9-2.1.0.dist-info/METADATA
saral_squarev9-2.1.0.dist-info/WHEEL
saral_squarev9-2.1.0.dist-info/entry_points.txt
saral_squarev9-2.1.0.dist-info/top_level.txt
saral_squarev9-2.1.0.dist-info/RECORD
