Metadata-Version: 2.1
Name: saral-squarev9
Version: 2.1.0
Summary: It squares the number
Home-page: https://github.com/uditvashisht/saral-square
Author: Udit Vashisht
Author-email: admin@saralgyaan.com
License: MIT
Platform: UNKNOWN
Classifier: License :: OSI Approved :: MIT License
Classifier: Programming Language :: Python :: 3.6
Classifier: Programming Language :: Python :: 3.7
Classifier: Programming Language :: Python :: 3.8
